metocean_stats/__init__.py
metocean_stats/CMA/__init__.py
metocean_stats/CMA/contours.py
metocean_stats/CMA/distributions.py
metocean_stats/CMA/jointmodel.py
metocean_stats/CMA/plotting.py
metocean_stats/CMA/predefined.py
metocean_stats/maps/__init__.py
metocean_stats/maps/maps.py
metocean_stats/plots/__init__.py
metocean_stats/plots/climate.py
metocean_stats/plots/dir.py
metocean_stats/plots/extreme.py
metocean_stats/plots/general.py
metocean_stats/plots/spectra.py
metocean_stats/plots/verification.py
metocean_stats/stats/__init__.py
metocean_stats/stats/aux_funcs.py
metocean_stats/stats/doc_funcs.py
metocean_stats/stats/extreme.py
metocean_stats/stats/general.py
metocean_stats/stats/profile.py
metocean_stats/stats/spec_funcs.py
metocean_stats/stats/verification.py
metocean_stats/tables/__init__.py
metocean_stats/tables/climate.py
metocean_stats/tables/dir.py
metocean_stats/tables/extreme.py
metocean_stats/tables/general.py
metocean_stats/tables/spectra.py
metocean_stats/tables/verification.py
metocean_stats-1.1.1.dist-info/licenses/LICENSE
tests/__init__.py
tests/test_climate.py
tests/test_joint.py
tests/test_maps.py
tests/test_plots.py
tests/test_tables.py
tests/test_verification.py
tests/data/NORA_test.txt
tests/data/NorkystDA_test.csv
tests/data/synthetic_dataset.py
metocean_stats-1.1.1.dist-info/METADATA
metocean_stats-1.1.1.dist-info/WHEEL
metocean_stats-1.1.1.dist-info/top_level.txt
metocean_stats-1.1.1.dist-info/RECORD
